MANIFEST.in
README.rst
setup.py
django_shop_multiplecurrencies.egg-info/PKG-INFO
django_shop_multiplecurrencies.egg-info/SOURCES.txt
django_shop_multiplecurrencies.egg-info/dependency_links.txt
django_shop_multiplecurrencies.egg-info/not-zip-safe
django_shop_multiplecurrencies.egg-info/requires.txt
django_shop_multiplecurrencies.egg-info/top_level.txt
shop_multiplecurrencies/__init__.py
shop_multiplecurrencies/fields.py
shop_multiplecurrencies/middleware.py
shop_multiplecurrencies/templatetags/__init__.py
shop_multiplecurrencies/templatetags/currency.py