Metadata-Version: 1.0
Name: django-shop-multiplecurrencies
Version: 1.0.0
Summary: Multiple currencies for Django Shop
Home-page: http://www.django-shop.org/
Author: Ales Kocjancic
Author-email: ales.kocjancic@divio.ch
License: BSD License
Platform: OS Independent
